halfred/__init__.py
halfred/client.py
halfred/exceptions.py
halfred/models.py
halfred-0.4.0.dist-info/licenses/LICENSE
halfred-0.4.0.dist-info/METADATA
halfred-0.4.0.dist-info/WHEEL
halfred-0.4.0.dist-info/top_level.txt
halfred-0.4.0.dist-info/RECORD
